githubcontribs/__init__.py
githubcontribs/_fetcher.py
githubcontribs/_plotter.py
githubcontribs-0.3.0.dist-info/LICENSE
githubcontribs-0.3.0.dist-info/WHEEL
githubcontribs-0.3.0.dist-info/METADATA
githubcontribs-0.3.0.dist-info/RECORD
