Metadata-Version: 2.3
Name: githubcontribs
Version: 0.3.0
Summary: Simple analytics for GitHub contributions across an organization.
Author-email: Lamin Labs <open-source@lamin.ai>
Requires-Python: >=3.10,<3.14
Requires-Dist: pandas
Requires-Dist: requests
Requires-Dist: dotenv
Requires-Dist: seaborn
Requires-Dist: tqdm
Requires-Dist: pre-commit ; extra == "dev"
Requires-Dist: nox ; extra == "dev"
Requires-Dist: pytest>=6.0 ; extra == "dev"
Requires-Dist: pytest-cov ; extra == "dev"
Requires-Dist: nbproject_test ; extra == "dev"
Project-URL: Home, https://github.com/laminlabs/githubcontribs
Provides-Extra: dev
